{"catan_46.jpg4225089":{"fileref":"","size":4225089,"filename":"catan_46.jpg","base64_img_data":"","file_attributes":{},"regions":{"0":{"shape_attributes":{"name":"polygon","all_points_x":[2288,1860,1878,1908,2288,2308,2288],"all_points_y":[794,899,984,996,907,881,794]},"region_attributes":{"type":"road","color":"red"}},"1":{"shape_attributes":{"name":"polygon","all_points_x":[1724,1670,1839,1885,1965,1931,1931,1814,1791,1724],"all_points_y":[1417,1473,1668,1652,1560,1527,1519,1370,1363,1417]},"region_attributes":{"type":"town","color":"red"}},"2":{"shape_attributes":{"name":"polygon","all_points_x":[2154,2175,2264,2172,2336,2521,2267,2154],"all_points_y":[1309,1424,1478,1614,1716,1414,1271,1309]},"region_attributes":{"type":"city","color":"red"}},"3":{"shape_attributes":{"name":"polygon","all_points_x":[2510,2500,2580,2708,2715,2510],"all_points_y":[1043,1199,1288,1196,1050,1043]},"region_attributes":{"type":"town","color":"red"}},"4":{"shape_attributes":{"name":"polygon","all_points_x":[2585,2659,2961,2882,2585],"all_points_y":[1381,1440,1078,1014,1381]},"region_attributes":{"type":"town","color":"red"}},"5":{"shape_attributes":{"name":"polygon","all_points_x":[1893,1998,2090,2062,1955,1837,1773,1893],"all_points_y":[1058,1066,1145,1199,1376,1360,1237,1058]},"region_attributes":{"type":"town","color":"red"}},"6":{"shape_attributes":{"name":"polygon","all_points_x":[2010,1995,1949,2022,2124,2172,2177,2010],"all_points_y":[2140,2171,2418,2459,2457,2208,2181,2140]},"region_attributes":{"type":"town","color":"red"}},"7":{"shape_attributes":{"name":"polygon","all_points_x":[2369,2362,2101,2164,2174,2440,2444,2369],"all_points_y":[2130,2142,2495,2545,2550,2213,2193,2130]},"region_attributes":{"type":"road","color":"red"}}}},"catan_47.jpg4279160":{"fileref":"","size":4279160,"filename":"catan_47.jpg","base64_img_data":"","file_attributes":{},"regions":{"0":{"shape_attributes":{"name":"polygon","all_points_x":[2326,2241,2241,2403,2408,2482,2482,2326],"all_points_y":[464,489,505,915,920,889,866,464]},"region_attributes":{"type":"road","color":"white"}},"1":{"shape_attributes":{"name":"polygon","all_points_x":[2019,2103,1860,1773,2019],"all_points_y":[1109,1173,1532,1478,1109]},"region_attributes":{"type":"road","color":"white"}},"2":{"shape_attributes":{"name":"polygon","all_points_x":[2152,2262,2346,2341,2357,2329,2236,2121,2152],"all_points_y":[1281,1281,1273,1273,1250,1004,1002,1037,1281]},"region_attributes":{"type":"town","color":"white"}},"3":{"shape_attributes":{"name":"polygon","all_points_x":[2006,2016,2060,2298,2262,2244,2006],"all_points_y":[820,922,1040,976,866,751,820]},"region_attributes":{"type":"town","color":"white"}},"4":{"shape_attributes":{"name":"polygon","all_points_x":[1780,1837,2177,2180,2116,2111,1780],"all_points_y":[1670,1747,1483,1470,1396,1409,1670]},"region_attributes":{"type":"road","color":"white"}},"5":{"shape_attributes":{"name":"polygon","all_points_x":[2101,2162,2149,1847,1793,1791,2101],"all_points_y":[1570,1629,1645,1942,1880,1857,1570]},"region_attributes":{"type":"road","color":"white"}},"6":{"shape_attributes":{"name":"polygon","all_points_x":[1703,1780,1796,1637,1537,1537,1693,1703],"all_points_y":[2428,2405,2382,1970,2013,2024,2418,2428]},"region_attributes":{"type":"road","color":"white"}},"7":{"shape_attributes":{"name":"polygon","all_points_x":[1791,1796,2226,2208,2216,2154,1803,1791],"all_points_y":[2454,2551,2508,2405,2398,2390,2436,2454]},"region_attributes":{"type":"road","color":"white"}},"8":{"shape_attributes":{"name":"polygon","all_points_x":[1883,2039,2062,2008,2085,2136,2126,2034,1796,1768,1870,1883],"all_points_y":[2416,2390,2346,2203,2180,2047,2039,1990,2049,2093,2405,2416]},"region_attributes":{"type":"city","color":"white"}},"9":{"shape_attributes":{"name":"polygon","all_points_x":[3097,3197,3151,3061,3043,3079,3097],"all_points_y":[1158,1166,1616,1601,1604,1160,1158]},"region_attributes":{"type":"road","color":"white"}},"10":{"shape_attributes":{"name":"polygon","all_points_x":[2321,2364,2738,2738,2692,2321],"all_points_y":[1880,1955,1734,1719,1655,1880]},"region_attributes":{"type":"road","color":"white"}},"11":{"shape_attributes":{"name":"polygon","all_points_x":[2131,2136,2211,2313,2305,2231,2131],"all_points_y":[2359,2375,2387,1960,1944,1926,2359]},"region_attributes":{"type":"road","color":"white"}},"12":{"shape_attributes":{"name":"polygon","all_points_x":[2375,2375,2416,2808,2769,2375],"all_points_y":[2054,2065,2157,1978,1883,2054]},"region_attributes":{"type":"road","color":"white"}}}},"catan_48.jpg4643839":{"fileref":"","size":4643839,"filename":"catan_48.jpg","base64_img_data":"","file_attributes":{},"regions":{}},"catan_49.jpg5076957":{"fileref":"","size":5076957,"filename":"catan_49.jpg","base64_img_data":"","file_attributes":{},"regions":{}},"catan_50.jpg5204619":{"fileref":"","size":5204619,"filename":"catan_50.jpg","base64_img_data":"","file_attributes":{},"regions":{}},"catan_51.jpg5263075":{"fileref":"","size":5263075,"filename":"catan_51.jpg","base64_img_data":"","file_attributes":{},"regions":{}},"catan_52.jpg3849736":{"fileref":"","size":3849736,"filename":"catan_52.jpg","base64_img_data":"","file_attributes":{},"regions":{}},"catan_53.jpg8727267":{"fileref":"","size":8727267,"filename":"catan_53.jpg","base64_img_data":"","file_attributes":{},"regions":{}}}